{
    "english": {
        "word": "bath",
        "examples": [
            "I'm going to take a bath now.",
            "She filled the bath with warm water."
        ],
        "gender": [
            "neuter"
        ],
        "trick-words": [
            "shower",
            "tub",
            "bathtub",
            "soak"
        ]
    },
    "portuguese": {
        "word": "banho",
        "examples": [
            "Vou tomar um banho agora.",
            "Ela encheu a banheira com água quente."
        ],
        "gender": [
            "masculine"
        ],
        "trick-words": [
            "ducha",
            "chuveiro",
            "banheira",
            "imersão"
        ]
    },
    "progress": {
        "memory": 0.4,
        "gender-memory": 0.6
    },
    "type": [
        "noun"
    ],
    "dates": {
        "discover-date": "",
        "next-review": "",
        "last-reviewed": ""
    },
    "synonyms": {
        "relaxation": {
            "user-made": [],
            "suggested": [
                "Taking a bath is a great way to relax after a long day."
            ]
        },
        "cleanliness": {
            "user-made": [],
            "suggested": [
                "I feel so clean after taking a bath."
            ]
        },
        "luxury": {
            "user-made": [],
            "suggested": [
                "Taking a bath in a jacuzzi tub feels like pure luxury."
            ]
        },
        "soothing": {
            "user-made": [],
            "suggested": [
                "Adding lavender oil to my bathwater is so soothing."
            ]
        },
        "meditative": {
            "user-made": [],
            "suggested": [
                "Taking a bath can be a meditative experience."
            ]
        },
        "pampering": {
            "user-made": [],
            "suggested": [
                "Treating yourself to a bubble bath is the ultimate pampering."
            ]
        },
        "therapeutic": {
            "user-made": [],
            "suggested": [
                "Epsom salt baths can be therapeutic for sore muscles."
            ]
        }
    }
}